pupil_labs/video/__init__.py
pupil_labs/video/array_like.py
pupil_labs/video/constants.py
pupil_labs/video/frame.py
pupil_labs/video/frame_slice.py
pupil_labs/video/indexing.py
pupil_labs/video/multi_reader.py
pupil_labs/video/py.typed
pupil_labs/video/reader.py
pupil_labs/video/writer.py
pupil_labs_video-1.0.6.dist-info/METADATA
pupil_labs_video-1.0.6.dist-info/WHEEL
pupil_labs_video-1.0.6.dist-info/licenses/LICENSE
pupil_labs_video-1.0.6.dist-info/RECORD
