Metadata-Version: 2.4
Name: pupil-labs-video
Version: 1.0.6
Summary: A high-level wrapper of PyAV providing an easy to use interface to video data.
Project-URL: Homepage, https://pupil-labs.github.io/pl-video
Project-URL: Documentation, https://pupil-labs.github.io/pl-video
Project-URL: Repository, https://github.com/pupil-labs/pl-video
Project-URL: Issues, https://github.com/pupil-labs/pl-video/issues
Author-email: Pupil Labs GmbH <info@pupil-labs.com>
License: MIT
License-File: LICENSE
Classifier: Intended Audience :: Developers
Classifier: Programming Language :: Python
Classifier: Programming Language :: Python :: 3
Classifier: Programming Language :: Python :: 3.10
Classifier: Programming Language :: Python :: 3.11
Classifier: Programming Language :: Python :: 3.12
Classifier: Programming Language :: Python :: 3.13
Classifier: Topic :: Software Development :: Libraries :: Python Modules
Requires-Python: <4.0,>=3.10
Requires-Dist: av
Requires-Dist: numpy
Requires-Dist: universal-pathlib
Provides-Extra: examples
Requires-Dist: opencv-python; extra == 'examples'
Requires-Dist: tqdm; extra == 'examples'
